{
  "users": [
    {
      "id": "admin_1",
      "username": "shanto",
      "password": "$2b$10$6tXfURe6TrhDp8XBP8mM8u6jkXpaHVcVQDznQ6xS5lRaQzvpJ/m6q",
      "isOwner": true,
      "credits": "9999899.00",
      "isActive": true,
      "createdAt": "2026-02-11T10:17:28.798Z",
      "lastActive": "2026-02-11T10:18:15.399Z"
    }
  ],
  "uids": [
    {
      "id": "repo_1770805095399_or6i8u250",
      "userId": "admin_1",
      "uidValue": "14295790811",
      "accountUsername": "ghfghfghfghf",
      "duration": -1,
      "cost": "100.00",
      "status": "active",
      "isActive": true,
      "createdAt": "2026-02-11T10:18:15.399Z",
      "expiresAt": "2126-02-11T10:18:15.399Z"
    }
  ],
  "activityLogs": [
    {
      "id": "repo_1770805084547_9ky47lqu9",
      "userId": "admin_1",
      "action": "login",
      "details": "User shanto logged in",
      "createdAt": "2026-02-11T10:18:04.547Z"
    },
    {
      "id": "repo_1770805095399_ein4och3d",
      "userId": "admin_1",
      "action": "create_uid",
      "details": "Created UID 14295790811 with Lifetime duration - Cost: $100.00",
      "createdAt": "2026-02-11T10:18:15.399Z"
    }
  ],
  "plans": [
    {
      "id": "1",
      "name": "1 Hour",
      "price": "0.50",
      "duration": 1,
      "isActive": true,
      "isPopular": false,
      "createdAt": "2026-02-11T10:17:28.738Z",
      "updatedAt": "2026-02-11T10:17:28.738Z"
    },
    {
      "id": "2",
      "name": "6 Hours",
      "price": "2.00",
      "duration": 6,
      "isActive": true,
      "isPopular": false,
      "createdAt": "2026-02-11T10:17:28.738Z",
      "updatedAt": "2026-02-11T10:17:28.738Z"
    },
    {
      "id": "3",
      "name": "12 Hours",
      "price": "3.50",
      "duration": 12,
      "isActive": true,
      "isPopular": true,
      "createdAt": "2026-02-11T10:17:28.738Z",
      "updatedAt": "2026-02-11T10:17:28.738Z"
    },
    {
      "id": "4",
      "name": "24 Hours",
      "price": "6.00",
      "duration": 24,
      "isActive": true,
      "isPopular": false,
      "createdAt": "2026-02-11T10:17:28.738Z",
      "updatedAt": "2026-02-11T10:17:28.738Z"
    },
    {
      "id": "5",
      "name": "3 Days",
      "price": "15.00",
      "duration": 72,
      "isActive": true,
      "isPopular": false,
      "createdAt": "2026-02-11T10:17:28.738Z",
      "updatedAt": "2026-02-11T10:17:28.738Z"
    },
    {
      "id": "6",
      "name": "7 Days",
      "price": "30.00",
      "duration": 168,
      "isActive": true,
      "isPopular": false,
      "createdAt": "2026-02-11T10:17:28.738Z",
      "updatedAt": "2026-02-11T10:17:28.738Z"
    },
    {
      "id": "7",
      "name": "Lifetime",
      "price": "100.00",
      "duration": -1,
      "isActive": true,
      "isPopular": true,
      "createdAt": "2026-02-11T10:17:28.738Z",
      "updatedAt": "2026-02-11T10:17:28.738Z"
    }
  ]
}